MANIFEST.in
README.md
setup.py
pybofh/__init__.py
pybofh/atomic_operations.py
pybofh/blockdevice.py
pybofh/btrfs.py
pybofh/encryption.py
pybofh/filesystem.py
pybofh/lvm.py
pybofh/misc.py
pybofh/mount.py
pybofh/settingsmodule.py
pybofh/shell.py
pybofh/xen.py
pybofh.egg-info/PKG-INFO
pybofh.egg-info/SOURCES.txt
pybofh.egg-info/dependency_links.txt
pybofh.egg-info/top_level.txt
pybofh/drbd/__init__.py
pybofh/drbd/classes.py
pybofh/drbd/drbdadm.py
pybofh/drbd/misc.py
pybofh/drbd/proc_parser.py
pybofh/tests/__init__.py
pybofh/tests/common.py
pybofh/tests/system_tests.py
pybofh/tests/test_atomic_operations.py
pybofh/tests/test_blockdevice.py
pybofh/tests/test_btrfs.py
pybofh/tests/test_encryption.py
pybofh/tests/test_filesystem.py
pybofh/tests/test_lvm.py
pybofh/tests/test_mount.py
pybofh/tests/test_settingsmodule.py
pybofh/tests/test_shell.py
pybofh/tests/test_xen.py