Metadata-Version: 1.1
Name: pybofh
Version: 0.2.1
Summary: A Linux system administration automation toolset
Home-page: https://github.com/goncalopp/pybofh
Author: Goncalo Pinheira
Author-email: goncalopp+pybofh@quorumverita.com
License: BSD
Keywords: linux sysadmin library toolset
Platform: UNKNOWN
Classifier: Development Status :: 4 - Beta
Classifier: Environment :: Console
Classifier: Intended Audience :: System Administrators
Classifier: Topic :: System :: Systems Administration
Classifier: Topic :: System :: Clustering
Classifier: Topic :: System :: Filesystems
Classifier: Topic :: System :: Monitoring
Classifier: License :: OSI Approved :: BSD License
Classifier: Operating System :: POSIX :: Linux
Classifier: Programming Language :: Python :: 2
Classifier: Programming Language :: Python :: 2.7
